rvcpu/sync_fifo/asserts_sync_fifo.sv
//assertion bind file to ensure fifo behavior
/* verilator lint_off UNUSED */
module asserts_sync_fifo(
	input logic clk,
	input logic rst,
	input logic write,
	input logic read,
	input logic [31:0]wData,
	input logic [31:0]rdData,
	input logic empty,
	input logic full
	);
	initial begin
		$display("hello from binded assertion module");
	end
	
	//property flags;
	//	@(posedge clk) disable iff (~rst)	
	//		!(empty == full);
	//endproperty
	//prop_status_flags: assert property(flags)
	//	else $display([SVA] full and empty fail);
	
	//propEmptyFullFlags: assert property (@(posedge clk) disable iff (~rst) (empty && full)) else begin
	//	//$error("[SVA] full and empty fail"); //error will abort sim
	//	$display("[SVA] full and empty fail, Full: %b Empty: %b", full, empty);
	//end
	propEmptyFullFlags: assert property (@(posedge clk) (empty && full)) else begin
		//$error("[SVA] full and empty fail"); //error will abort sim
		$display("[SVA] full and empty fail, Full: %b Empty: %b", full, empty);
	end
	
	//propEmptyFullFlags: assert property (@(posedge clk) write |-> ##0 wData != 0) else begin
	//	//$error("[SVA] full and empty fail"); //error will abort sim
	//	$display("[SVA] full and empty fail, Full: %b Empty: %b", full, empty);
	//end
	always@(posedge clk) begin
		$display("COUNT: %d", sync_fifo.count);
	end

endmodule
/* verilator lint_on UNUSED */

rvcpu/sync_fifo/sync_fifo.sv
//basic sync_fifo as the baseline for the scheduling queue and ROB
module sync_fifo(
	input logic clk,
	input logic rst,
	input logic write,
	input logic read,
	input logic [31:0]wData,
	output logic [31:0]rdData,
	output logic empty,
	output logic full
	);
	
	bind sync_fifo asserts_sync_fifo test(clk, rst, write, read, wData, rdData, empty, full);

	logic [31:0] mem [0:7];

	logic [2:0]w_ptr;
	logic [2:0]r_ptr;

	byte count;
	assign full = count == 8;
	assign empty = count == 0;
	//Read block
	always@(posedge clk or negedge rst) begin
		if(~rst) begin
			r_ptr <= 0;
		end
		else if (read && ~empty) begin
			rdData <= mem[r_ptr];
			if(r_ptr == 7) begin
				r_ptr <= 0;
			end
			else begin
				r_ptr <= r_ptr + 1;
			end
		end 
	end
	//Write block
	always@(posedge clk or negedge rst) begin
		if(~rst) begin
			w_ptr <= 0;
		end
		else if (write && ~full) begin
			mem[w_ptr] <= wData;
			if(w_ptr == 7 && ~full) begin
				w_ptr <= 0;
			end
			else begin
				w_ptr <= w_ptr + 1;
			end 
		end
	end
	//Fifo elements counter
	always@(posedge clk or negedge rst) begin
		if(~rst) begin
			count <= 0;
		end
		else if(read && !write && count != 0) begin
			count <= count - 1;
		end
		else if(write && !read && count != 8) begin
			count <= count + 1;
		end
	end 
endmodule

rvcpu/sync_fifo/Dump.vcd
$version Generated by VerilatedVcd $end
$date Mon Oct  4 20:09:55 2021 $end
$timescale 1ps $end

 $scope module TOP $end
  $var wire  1 . clk $end
  $var wire  1 4 empty $end
  $var wire  1 5 full $end
  $var wire 32 3 rdData [31:0] $end
  $var wire  1 1 read $end
  $var wire  1 / rst $end
  $var wire 32 2 wData [31:0] $end
  $var wire  1 0 write $end
  $scope module sync_fifo $end
   $var wire  1 . clk $end
   $var wire  8 - count [7:0] $end
   $var wire  1 4 empty $end
   $var wire  1 5 full $end
   $var wire 32 # mem[0] [31:0] $end
   $var wire 32 $ mem[1] [31:0] $end
   $var wire 32 % mem[2] [31:0] $end
   $var wire 32 & mem[3] [31:0] $end
   $var wire 32 ' mem[4] [31:0] $end
   $var wire 32 ( mem[5] [31:0] $end
   $var wire 32 ) mem[6] [31:0] $end
   $var wire 32 * mem[7] [31:0] $end
   $var wire  3 , r_ptr [2:0] $end
   $var wire 32 3 rdData [31:0] $end
   $var wire  1 1 read $end
   $var wire  1 / rst $end
   $var wire 32 2 wData [31:0] $end
   $var wire  3 + w_ptr [2:0] $end
   $var wire  1 0 write $end
   $scope module test $end
    $var wire  1 . clk $end
    $var wire  1 4 empty $end
    $var wire  1 5 full $end
    $var wire 32 3 rdData [31:0] $end
    $var wire  1 1 read $end
    $var wire  1 / rst $end
    $var wire 32 2 wData [31:0] $end
    $var wire  1 0 write $end
   $upscope $end
  $upscope $end
 $upscope $end
$enddefinitions $end


#8
b00000000000000000000000000000000 #
b00000000000000000000000000000000 $
b00000000000000000000000000000000 %
b00000000000000000000000000000000 &
b00000000000000000000000000000000 '
b00000000000000000000000000000000 (
b00000000000000000000000000000000 )
b00000000000000000000000000000000 *
b000 +
b000 ,
b00000000 -
0.
0/
00
01
b00000000000000000000000000000000 2
b00000000000000000000000000000000 3
14
05
#10
1.
#15
0.
#18
1/
10
b01111111111111111111111111111111 2
#20
b01111111111111111111111111111111 #
b001 +
b00000001 -
1.
04
#25
0.
#28
b10000000000000000000000000000000 2
#30
b10000000000000000000000000000000 $
b010 +
b00000010 -
1.
#35
0.
#38
00
11
#40
b001 ,
b00000001 -
1.
b01111111111111111111111111111111 3
#45
0.
#48
#50
b010 ,
b00000000 -
1.
b10000000000000000000000000000000 3
14
